{
  "name": "no_mitigation",
  "data": [
    {
      "seriesName": "RSDAHT",
      "seriesValues": [
        [
          2018,
          0.765181804012652
        ],
        [
          2019,
          1.4709164293632184
        ],
        [
          2020,
          1.8696426638031962
        ],
        [
          2021,
          1.8313835736025625
        ],
        [
          2022,
          1.7931244834019295
        ],
        [
          2023,
          1.7548653932012979
        ],
        [
          2024,
          1.7166063030006642
        ],
        [
          2025,
          1.6783472128000307
        ],
        [
          2026,
          1.640088122599398
        ],
        [
          2027,
          1.6018290323987656
        ],
        [
          2028,
          1.5635699421981324
        ],
        [
          2029,
          1.5253108519974992
        ],
        [
          2030,
          1.487051761796866
        ],
        [
          2031,
          1.4487926715962334
        ],
        [
          2032,
          1.4105335813956008
        ],
        [
          2033,
          1.3722744911949682
        ],
        [
          2034,
          1.3340154009943355
        ],
        [
          2035,
          1.2957563107937022
        ],
        [
          2036,
          1.2574972205930703
        ],
        [
          2037,
          1.2192381303924376
        ],
        [
          2038,
          1.1809790401918094
        ],
        [
          2039,
          0.4369853246406105
        ]
      ]
    },
    {
      "seriesName": "RSDAHT2",
      "seriesValues": [
        [
          2018,
          0.9121654910333858
        ],
        [
          2019,
          0.90016702688494
        ],
        [
          2020,
          0.8831074143384414
        ],
        [
          2021,
          0.87163711395708
        ],
        [
          2022,
          0.8218746112678965
        ],
        [
          2023,
          0.7705074480636526
        ],
        [
          2024,
          0.7191402848594077
        ],
        [
          2025,
          0.6677731216551642
        ],
        [
          2026,
          0.6164059584509204
        ],
        [
          2027,
          0.565038795246676
        ],
        [
          2028,
          0.5136716320424329
        ],
        [
          2029,
          0.4623044688381893
        ],
        [
          2030,
          0.4109373056339453
        ],
        [
          2031,
          0.3595701424297014
        ],
        [
          2032,
          0.3082029792254571
        ],
        [
          2033,
          0.2568358160212138
        ],
        [
          2034,
          0.2054686528169693
        ],
        [
          2035,
          0.1541014896127254
        ],
        [
          2036,
          0.10273432640848254
        ],
        [
          2037,
          0.05136716320423863
        ]
      ]
    },
    {
      "seriesName": "RSDBDL",
      "seriesValues": [
        [
          2018,
          8.03674919399263e-05
        ],
        [
          2019,
          7.634911734293e-05
        ],
        [
          2020,
          0.3681059968925323
        ],
        [
          2021,
          3.3517533490398415
        ],
        [
          2022,
          3.0922442843174225
        ],
        [
          2023,
          3.6161407388960547
        ],
        [
          2024,
          3.6747678535637656
        ],
        [
          2025,
          3.6483954710536275
        ],
        [
          2026,
          3.674750144074722
        ],
        [
          2027,
          3.264921569547533
        ],
        [
          2028,
          2.73203168129133
        ],
        [
          2029,
          3.5052348494204693
        ],
        [
          2030,
          1.2906548309552455
        ],
        [
          2031,
          2.81286221789742e-05
        ],
        [
          2032,
          2.41102475819779e-05
        ],
        [
          2033,
          2.00918729849816e-05
        ]
      ]
    },
    {
      "seriesName": "RSDBGS",
      "seriesValues": [
        [
          2018,
          0.0132224319786942
        ],
        [
          2020,
          0.625387481069335
        ],
        [
          2021,
          0.388088053482405
        ],
        [
          2022,
          0.528327913061849
        ],
        [
          2023,
          0.511801786111471
        ],
        [
          2024,
          0.4704020609112
        ],
        [
          2025,
          0.476173540854443
        ],
        [
          2026,
          0.162726911090043
        ],
        [
          2033,
          0.106624538896275
        ],
        [
          2034,
          0.113516595169525
        ],
        [
          2035,
          0.257925811371945
        ],
        [
          2036,
          0.127552478950599
        ],
        [
          2037,
          0.134701898742114
        ],
        [
          2038,
          0.141940615821881
        ]
      ]
    },
    {
      "seriesName": "RSDCOA",
      "seriesValues": [
        [
          2018,
          9.100000000000001
        ],
        [
          2019,
          7.799999999999999
        ],
        [
          2020,
          8.2
        ],
        [
          2021,
          7.800000000000001
        ],
        [
          2022,
          9.079999999999991
        ],
        [
          2023,
          10.487999999999996
        ],
        [
          2024,
          12.036800000000001
        ],
        [
          2025,
          13.74048000000001
        ],
        [
          2026,
          15.614528000000009
        ],
        [
          2027,
          17.67598079999999
        ],
        [
          2028,
          19.943578880000054
        ],
        [
          2029,
          22.43793676800002
        ],
        [
          2030,
          25.18173044480001
        ],
        [
          2031,
          28.19990348927995
        ],
        [
          2032,
          31.519893838208066
        ],
        [
          2033,
          35.171883222028846
        ],
        [
          2034,
          39.18907154423169
        ],
        [
          2035,
          43.607978698654904
        ],
        [
          2036,
          48.46877656852041
        ],
        [
          2037,
          53.81565422537245
        ],
        [
          2038,
          59.6972196479097
        ],
        [
          2039,
          66.1669416127006
        ],
        [
          2040,
          73.2836357739707
        ],
        [
          2041,
          81.1119993513678
        ],
        [
          2042,
          89.72319928650465
        ],
        [
          2043,
          99.19551921515512
        ],
        [
          2044,
          109.61507113667093
        ],
        [
          2045,
          113.14428046780978
        ],
        [
          2046,
          112.73389942472576
        ],
        [
          2047,
          112.29524846592217
        ],
        [
          2048,
          111.84526257251434
        ],
        [
          2049,
          111.38277367625287
        ],
        [
          2050,
          110.90785925702983
        ]
      ]
    },
    {
      "seriesName": "RSDELC",
      "seriesValues": [
        [
          2018,
          5.050868078998525
        ],
        [
          2019,
          5.832438618727808
        ],
        [
          2020,
          6.323482638076933
        ],
        [
          2021,
          6.1622966892691995
        ],
        [
          2022,
          6.015234541133969
        ],
        [
          2023,
          5.771103987678347
        ],
        [
          2024,
          5.426616419050339
        ],
        [
          2025,
          5.082035336069308
        ],
        [
          2026,
          4.4655733821310335
        ],
        [
          2027,
          4.143635202488111
        ],
        [
          2028,
          3.64812201610802
        ],
        [
          2029,
          3.343608376616888
        ],
        [
          2030,
          2.0826259642019704
        ],
        [
          2031,
          1.6210328183900569
        ],
        [
          2032,
          1.4754318147698062
        ],
        [
          2033,
          1.3298084404387298
        ],
        [
          2034,
          1.184143962858588
        ],
        [
          2035,
          1.0384062204303368
        ],
        [
          2036,
          0.8925973880244988
        ],
        [
          2037,
          0.7467611633470767
        ],
        [
          2038,
          0.6008891664219735
        ],
        [
          2039,
          0.250084508287097
        ],
        [
          2040,
          0.047067885838305505
        ],
        [
          2041,
          0.04715064490232278
        ],
        [
          2042,
          0.048266633517501246
        ],
        [
          2043,
          0.04936866901333318
        ],
        [
          2044,
          0.05045387124962511
        ],
        [
          2045,
          0.0515123499108361
        ],
        [
          2046,
          0.052525000476011885
        ],
        [
          2047,
          0.053494851920381316
        ],
        [
          2048,
          0.05440351098889317
        ],
        [
          2049,
          0.05526112179736276
        ],
        [
          2050,
          0.05607247186304434
        ]
      ]
    },
    {
      "seriesName": "RSDETH",
      "seriesValues": [
        [
          2018,
          2.24993209633258e-05
        ],
        [
          2019,
          9.284848455018818e-05
        ],
        [
          2020,
          8.79462624367488e-05
        ],
        [
          2021,
          8.307495986069472e-05
        ],
        [
          2022,
          7.81744554993323e-05
        ],
        [
          2023,
          0.0001070556649462124
        ],
        [
          2024,
          9.99186206164649e-05
        ],
        [
          2025,
          9.278157628671741e-05
        ],
        [
          2026,
          5.86308416244993e-05
        ],
        [
          2027,
          5.3744938155791e-05
        ],
        [
          2028,
          4.88590346870827e-05
        ],
        [
          2029,
          4.39731312183744e-05
        ],
        [
          2030,
          3.908722774966612e-05
        ],
        [
          2037,
          2.25114086103922e-06
        ]
      ]
    },
    {
      "seriesName": "RSDGAS",
      "seriesValues": [
        [
          2018,
          23.96398194039434
        ],
        [
          2019,
          23.836070711564897
        ],
        [
          2020,
          23.48889508801187
        ],
        [
          2021,
          23.542931047166338
        ],
        [
          2022,
          26.29895026483947
        ],
        [
          2023,
          29.35556682558657
        ],
        [
          2024,
          32.74339576031895
        ],
        [
          2025,
          36.49682458630881
        ],
        [
          2026,
          40.64922167094572
        ],
        [
          2027,
          45.24129485225886
        ],
        [
          2028,
          49.10685276175912
        ],
        [
          2029,
          51.338550046739506
        ],
        [
          2030,
          54.97218108426562
        ],
        [
          2031,
          53.180582336779295
        ],
        [
          2032,
          48.24365129049845
        ],
        [
          2033,
          42.83982217830141
        ],
        [
          2034,
          39.446483364549074
        ],
        [
          2035,
          36.837715218128096
        ],
        [
          2036,
          34.08224718922798
        ],
        [
          2037,
          30.896460716478387
        ],
        [
          2038,
          27.64374677963921
        ],
        [
          2039,
          24.7355549243635
        ],
        [
          2040,
          22.360275582447898
        ],
        [
          2041,
          19.275320322447033
        ],
        [
          2042,
          16.05264385104259
        ],
        [
          2043,
          12.630741856771305
        ],
        [
          2044,
          9.030598579822144
        ],
        [
          2045,
          8.035174455535916
        ],
        [
          2046,
          8.004789599578393
        ],
        [
          2047,
          7.981602854495322
        ],
        [
          2048,
          7.963740482693174
        ],
        [
          2049,
          7.947813808490916
        ],
        [
          2050,
          7.932551679780593
        ]
      ]
    },
    {
      "seriesName": "RSDHET",
      "seriesValues": [
        [
          2018,
          0.1691682349811559
        ],
        [
          2019,
          0.349999999999997
        ],
        [
          2020,
          0.349999999999997
        ],
        [
          2021,
          0.3499999999999952
        ],
        [
          2022,
          0.8849999999999918
        ],
        [
          2023,
          1.4734999999999885
        ],
        [
          2024,
          2.120849999999986
        ],
        [
          2025,
          2.8329349999999813
        ],
        [
          2026,
          2.89617143558966
        ],
        [
          2027,
          3.0304818712157977
        ],
        [
          2028,
          3.8335300583373755
        ],
        [
          2029,
          4.716883064171114
        ],
        [
          2030,
          5.688571370588227
        ],
        [
          2031,
          6.757428507647058
        ],
        [
          2032,
          7.933171358411765
        ],
        [
          2033,
          9.226488494252944
        ],
        [
          2034,
          10.386705422134433
        ],
        [
          2035,
          10.783509735903667
        ],
        [
          2036,
          11.140381528193727
        ],
        [
          2037,
          11.367860849997749
        ],
        [
          2038,
          11.435417261998682
        ],
        [
          2039,
          11.435417261998685
        ],
        [
          2040,
          11.435417261998687
        ],
        [
          2041,
          11.435417261998678
        ],
        [
          2042,
          11.435417261998698
        ],
        [
          2043,
          11.435417261998685
        ],
        [
          2044,
          11.435417261998683
        ],
        [
          2045,
          11.135417261998684
        ],
        [
          2046,
          11.130182279503366
        ],
        [
          2047,
          11.130182279503373
        ],
        [
          2048,
          11.130182279503368
        ],
        [
          2049,
          11.130182279503373
        ],
        [
          2050,
          11.130182279503375
        ]
      ]
    },
    {
      "seriesName": "RSDKER",
      "seriesValues": [
        [
          2018,
          47.4000810035531
        ],
        [
          2019,
          47.082599148841226
        ],
        [
          2020,
          44.78501359921665
        ],
        [
          2021,
          42.31173966192761
        ],
        [
          2022,
          37.55506792316495
        ],
        [
          2023,
          31.558665381939495
        ],
        [
          2024,
          25.81579771542913
        ],
        [
          2025,
          19.844777628917278
        ],
        [
          2026,
          14.36133513353903
        ],
        [
          2027,
          8.35633298897413
        ],
        [
          2028,
          5.79215414935814
        ],
        [
          2029,
          2.001934636738742
        ]
      ]
    },
    {
      "seriesName": "RSDLPG",
      "seriesValues": [
        [
          2018,
          2.089941979292699
        ],
        [
          2019,
          2.0631355113408376
        ],
        [
          2020,
          2.3657683384305517
        ],
        [
          2021,
          2.068401165520269
        ],
        [
          2022,
          2.0307209926807253
        ],
        [
          2023,
          2.0430083193114834
        ],
        [
          2024,
          2.026951507587575
        ],
        [
          2025,
          1.6770987404142548
        ],
        [
          2026,
          1.570548874468656
        ],
        [
          2027,
          1.4414185717324624
        ],
        [
          2028,
          1.3024303196522808
        ],
        [
          2029,
          0.5004415469320864
        ],
        [
          2030,
          0.1853253900538763
        ],
        [
          2035,
          0.0061583009428897
        ],
        [
          2036,
          0.0041055339619265
        ],
        [
          2037,
          0.0177662597899704
        ]
      ]
    },
    {
      "seriesName": "RSDPEA",
      "seriesValues": [
        [
          2018,
          8.16197886262212
        ],
        [
          2019,
          7.699999999999996
        ],
        [
          2020,
          8.000000000000004
        ],
        [
          2021,
          7.600000000000003
        ],
        [
          2022,
          8.859999999999996
        ],
        [
          2023,
          10.245999999999995
        ],
        [
          2024,
          11.770599999999991
        ],
        [
          2025,
          13.447660000000004
        ],
        [
          2026,
          15.292425999999994
        ],
        [
          2027,
          17.321668599999995
        ],
        [
          2028,
          19.553835460000005
        ],
        [
          2029,
          22.00921900600004
        ],
        [
          2030,
          24.710140906599996
        ],
        [
          2031,
          27.681154997259995
        ],
        [
          2032,
          30.949270496986017
        ],
        [
          2033,
          34.16112064335765
        ],
        [
          2034,
          34.16112064335768
        ],
        [
          2035,
          34.16112064335772
        ],
        [
          2036,
          34.16112064335774
        ],
        [
          2037,
          34.16112064335767
        ],
        [
          2038,
          34.16112064335772
        ],
        [
          2039,
          34.161120643357656
        ],
        [
          2040,
          34.161120643357656
        ],
        [
          2041,
          34.161120643357656
        ],
        [
          2042,
          34.1611206433577
        ],
        [
          2043,
          34.1611206433577
        ],
        [
          2044,
          34.1611206433577
        ],
        [
          2045,
          34.1611206433577
        ],
        [
          2046,
          34.1611206433577
        ],
        [
          2047,
          34.1611206433577
        ],
        [
          2048,
          34.1611206433577
        ],
        [
          2049,
          34.1611206433577
        ],
        [
          2050,
          34.1611206433577
        ]
      ]
    },
    {
      "seriesName": "RSDSOL",
      "seriesValues": [
        [
          2018,
          0.5601767135600085
        ],
        [
          2019,
          0.5321678778820075
        ],
        [
          2020,
          0.5041590422040064
        ],
        [
          2021,
          0.4761502065260064
        ],
        [
          2022,
          0.44814137084800637
        ],
        [
          2023,
          0.4201325351700064
        ],
        [
          2024,
          0.3921236994920063
        ],
        [
          2025,
          0.36411486381400426
        ],
        [
          2026,
          0.3361060281360043
        ],
        [
          2027,
          0.30809719245800427
        ],
        [
          2028,
          0.2800883567800042
        ],
        [
          2029,
          0.2520795211020042
        ],
        [
          2030,
          0.2240706854240022
        ],
        [
          2031,
          0.19606184974600271
        ],
        [
          2032,
          0.1680530140680023
        ],
        [
          2033,
          0.14004417839000188
        ],
        [
          2034,
          0.1120353427120015
        ],
        [
          2035,
          0.0840265070340011
        ],
        [
          2036,
          0.056017671356000796
        ],
        [
          2037,
          0.028008835678000398
        ]
      ]
    },
    {
      "seriesName": "RSDWOO",
      "seriesValues": [
        [
          2018,
          1.2639359042693386
        ],
        [
          2019,
          1.1000000000000008
        ],
        [
          2020,
          1.1
        ],
        [
          2021,
          1.1999999999999946
        ],
        [
          2022,
          1.8199999999999994
        ],
        [
          2023,
          2.5019999999999847
        ],
        [
          2024,
          3.2521999999999993
        ],
        [
          2025,
          4.077420000000004
        ],
        [
          2026,
          4.985162000000003
        ],
        [
          2027,
          5.983678200000002
        ],
        [
          2028,
          1.917909298034222
        ],
        [
          2029,
          0.5707322159065762
        ],
        [
          2030,
          0.5073175252502902
        ],
        [
          2031,
          0.2552612148488026
        ],
        [
          2032,
          0.2187953270132595
        ],
        [
          2033,
          0.1823294391777162
        ],
        [
          2034,
          0.1458635513421732
        ],
        [
          2035,
          0.10939766350662994
        ],
        [
          2036,
          0.07293177567108645
        ],
        [
          2037,
          0.036465887835543075
        ]
      ]
    }
  ]
}