{
  "name": "no_mitigation",
  "data": [
    {
      "seriesName": "DMD_TRA-F-HTRUCK-ICE",
      "seriesValues": [
        [
          2019,
          1.325
        ],
        [
          2021,
          2.364
        ],
        [
          2022,
          2.225
        ],
        [
          2023,
          2.26760715768235
        ],
        [
          2024,
          2.2370213571291497
        ],
        [
          2025,
          1.89994733972723
        ],
        [
          2026,
          1.044559851554949
        ],
        [
          2027,
          0.448173747336266
        ],
        [
          2028,
          0.562252417721171
        ]
      ]
    },
    {
      "seriesName": "DMD_TRA-F-HTRUCK-HEV",
      "seriesValues": [
        [
          2023,
          0.2277
        ],
        [
          2024,
          0.34489914439638
        ],
        [
          2025,
          0.52918579619492
        ],
        [
          2026,
          0.808924837123863
        ],
        [
          2027,
          1.22796667138581
        ],
        [
          2028,
          1.85814597764324
        ],
        [
          2029,
          2.53157920694728
        ],
        [
          2030,
          2.75975566680834
        ],
        [
          2031,
          3.44841001761414
        ],
        [
          2032,
          4.13480457525878
        ],
        [
          2033,
          4.73435345193359
        ],
        [
          2034,
          5.19592291151472
        ],
        [
          2035,
          5.3627663760068
        ],
        [
          2036,
          5.07723619884081
        ],
        [
          2037,
          4.67209804952844
        ],
        [
          2038,
          4.15395358346043
        ],
        [
          2039,
          3.8196972491894
        ],
        [
          2040,
          2.96866761612734
        ],
        [
          2041,
          2.63917731924301
        ],
        [
          2042,
          1.5593498946603
        ]
      ]
    },
    {
      "seriesName": "DMD_TRA-F-HTRUCK-BEV",
      "seriesValues": [
        [
          2035,
          0.110985757664656
        ],
        [
          2036,
          0.284825322083802
        ],
        [
          2037,
          0.434724325236712
        ],
        [
          2038,
          0.665536474305956
        ],
        [
          2039,
          1.01317461959531
        ],
        [
          2040,
          1.53512928785295
        ],
        [
          2041,
          2.31896934551393
        ],
        [
          2042,
          3.49582527012081
        ],
        [
          2043,
          5.26348218267736
        ],
        [
          2044,
          5.41461589061903
        ],
        [
          2045,
          5.54756318611594
        ],
        [
          2046,
          5.56897352764667
        ],
        [
          2047,
          5.62384126681937
        ],
        [
          2048,
          5.81521667886596
        ],
        [
          2049,
          5.88528626205877
        ],
        [
          2050,
          5.98067084912886
        ]
      ]
    }
  ]
}