{
  "name": "mitigation_sectoralcbs-led",
  "data": [
    {
      "seriesName": "INDDST",
      "seriesValues": [
        [
          2018,
          0.0715262982135066
        ],
        [
          2019,
          0.0504931619626895
        ],
        [
          2020,
          0.0529633103004249
        ],
        [
          2021,
          0.0537405242837896
        ],
        [
          2022,
          0.0840137539743848
        ],
        [
          2023,
          0.062477234266657
        ],
        [
          2024,
          0.05790728281610575
        ],
        [
          2025,
          0.0534921150908668
        ],
        [
          2026,
          0.07580379064265019
        ],
        [
          2027,
          0.0737400076384834
        ],
        [
          2028,
          0.0716762246343171
        ],
        [
          2029,
          0.0547569530938382
        ],
        [
          2030,
          0.033774329312991
        ],
        [
          2031,
          0.0429677386542178
        ],
        [
          2032,
          0.0394447668147714
        ],
        [
          2033,
          0.0266031212517929
        ],
        [
          2034,
          0.0243778212050595
        ],
        [
          2035,
          0.0222350724784936
        ],
        [
          2036,
          0.020174875072093704
        ],
        [
          2037,
          0.018197228985860833
        ],
        [
          2038,
          0.01630213421979451
        ],
        [
          2039,
          0.014489590773894853
        ],
        [
          2040,
          0.0127595986481625
        ],
        [
          2041,
          0.0111121578425964
        ],
        [
          2042,
          0.009547268357196801
        ],
        [
          2043,
          0.0080649301919639
        ],
        [
          2044,
          0.0066651433468975
        ],
        [
          2045,
          0.0053479078219979
        ],
        [
          2046,
          0.0041132236172651
        ],
        [
          2047,
          0.0029610907326988
        ],
        [
          2048,
          0.0018915091682991999
        ],
        [
          2049,
          0.0009044789240661001
        ]
      ]
    },
    {
      "seriesName": "INDELC",
      "seriesValues": [
        [
          2018,
          0.7131713976321382
        ],
        [
          2019,
          0.7425289191850062
        ],
        [
          2020,
          0.6915378009466886
        ],
        [
          2021,
          0.6916636617363848
        ],
        [
          2022,
          1.0812931485982984
        ],
        [
          2023,
          1.05474564653664
        ],
        [
          2024,
          1.028198144474982
        ],
        [
          2025,
          1.0016506424133234
        ],
        [
          2026,
          0.9750624075248827
        ],
        [
          2027,
          0.9485160144277618
        ],
        [
          2028,
          0.9219696213306406
        ],
        [
          2029,
          0.8954232282335203
        ],
        [
          2030,
          0.8688768351363995
        ],
        [
          2031,
          0.8476397206587031
        ],
        [
          2032,
          0.8264026061810066
        ],
        [
          2033,
          0.8051654917033101
        ],
        [
          2034,
          0.7839283772256136
        ],
        [
          2035,
          0.7626912627479171
        ],
        [
          2036,
          0.7414541482702209
        ],
        [
          2037,
          0.7202170337925244
        ],
        [
          2038,
          0.698979919314828
        ],
        [
          2039,
          0.6777428048371313
        ],
        [
          2040,
          0.6565056903594353
        ],
        [
          2041,
          0.6352685758817385
        ],
        [
          2042,
          0.6140314614040419
        ],
        [
          2043,
          0.5927943469263448
        ],
        [
          2044,
          0.5715572324486489
        ],
        [
          2045,
          0.5503201179709525
        ],
        [
          2046,
          0.5290830034932558
        ],
        [
          2047,
          0.5078458890155593
        ],
        [
          2048,
          0.4866087745378638
        ],
        [
          2049,
          0.46537166006016667
        ],
        [
          2050,
          0.4441345455824703
        ]
      ]
    },
    {
      "seriesName": "INDGAS",
      "seriesValues": [
        [
          2018,
          0.5898710182364864
        ],
        [
          2019,
          0.6141068316125377
        ],
        [
          2020,
          0.6357938802685104
        ],
        [
          2021,
          0.6109661970457249
        ],
        [
          2022,
          0.9551370115819214
        ],
        [
          2023,
          0.8449736795396952
        ],
        [
          2024,
          0.7824490372290736
        ],
        [
          2025,
          0.7275584896266324
        ],
        [
          2026,
          0.7737594686273539
        ],
        [
          2027,
          0.8378861910389105
        ],
        [
          2028,
          0.814433775831265
        ],
        [
          2029,
          0.7909858628217072
        ],
        [
          2030,
          0.7609219456030457
        ],
        [
          2031,
          0.5208140930724334
        ],
        [
          2032,
          0.5072849837624651
        ],
        [
          2033,
          0.4649948995905897
        ],
        [
          2034,
          0.44746571694641507
        ],
        [
          2035,
          0.4466398778495262
        ],
        [
          2036,
          0.418250790630873
        ],
        [
          2037,
          0.38678372497677876
        ],
        [
          2038,
          0.3601999459936298
        ],
        [
          2039,
          0.3347461804791159
        ],
        [
          2040,
          0.1449835964610714
        ],
        [
          2041,
          0.1262642072754151
        ],
        [
          2042,
          0.1084828246541032
        ],
        [
          2043,
          0.0916394485971361
        ],
        [
          2044,
          0.0757340791045125
        ],
        [
          2045,
          0.0607667161762331
        ],
        [
          2046,
          0.0467373598122981
        ],
        [
          2047,
          0.0336460100127074
        ],
        [
          2048,
          0.0214926667774612
        ],
        [
          2049,
          0.010277330106557476
        ],
        [
          2050,
          1.7473364415618e-05
        ]
      ]
    },
    {
      "seriesName": "INDKER",
      "seriesValues": [
        [
          2018,
          0.006039082015554646
        ],
        [
          2019,
          0.011610886902931687
        ],
        [
          2020,
          0.014151843343604911
        ],
        [
          2021,
          0.012322760003781711
        ],
        [
          2022,
          0.019264444123695
        ],
        [
          2023,
          0.014328496445715403
        ],
        [
          2024,
          0.013280910595615756
        ],
        [
          2025,
          0.012268797748657023
        ],
        [
          2026,
          0.0173725506228309
        ],
        [
          2027,
          0.0168995772476146
        ],
        [
          2028,
          0.0164266038723984
        ],
        [
          2029,
          0.015953630497182264
        ],
        [
          2030,
          0.007740328560983583
        ],
        [
          2031,
          0.007173582250352248
        ],
        [
          2032,
          0.0066257548747295
        ],
        [
          2033,
          0.006096846434115581
        ],
        [
          2034,
          0.00558685692851018
        ],
        [
          2035,
          0.0050957863579133
        ],
        [
          2036,
          0.004623634722325377
        ],
        [
          2037,
          0.004170402021745977
        ],
        [
          2038,
          0.0037360882561752753
        ],
        [
          2039,
          0.003320693425613
        ],
        [
          2040,
          0.0029242175300595733
        ],
        [
          2041,
          0.002546660569514389
        ],
        [
          2042,
          0.0021880225439784885
        ],
        [
          2043,
          0.0018483034534508645
        ],
        [
          2044,
          0.0015275032979320765
        ],
        [
          2045,
          0.0012256220774216273
        ],
        [
          2046,
          0.0009426597919200525
        ],
        [
          2047,
          0.0006786164414271737
        ],
        [
          2048,
          0.0004334920259427304
        ],
        [
          2049,
          0.0002072865454670583
        ]
      ]
    },
    {
      "seriesName": "INDLPG",
      "seriesValues": [
        [
          2018,
          0.0923390369646781
        ],
        [
          2019,
          0.0755828390669689
        ],
        [
          2020,
          0.06903231132553381
        ],
        [
          2021,
          0.0759446064945924
        ],
        [
          2022,
          0.1187258883449841
        ],
        [
          2023,
          0.115810975058336
        ],
        [
          2024,
          0.1128960617716883
        ],
        [
          2025,
          0.10998114848504009
        ],
        [
          2026,
          0.1070662351983923
        ],
        [
          2027,
          0.1041513219117438
        ],
        [
          2028,
          0.1012364086250958
        ],
        [
          2029,
          0.0983214953384476
        ],
        [
          2030,
          0.0954065820517995
        ],
        [
          2031,
          0.0930746514224812
        ],
        [
          2032,
          0.0907427207931627
        ],
        [
          2033,
          0.0884107901638442
        ],
        [
          2034,
          0.0860788595345259
        ],
        [
          2035,
          0.0837469289052076
        ],
        [
          2036,
          0.0814149982758887
        ],
        [
          2037,
          0.0790830676465705
        ],
        [
          2038,
          0.0767511370172522
        ],
        [
          2039,
          0.0744192063879337
        ],
        [
          2040,
          0.0720872757586154
        ],
        [
          2041,
          0.0697553451292968
        ],
        [
          2042,
          0.0674234144999782
        ],
        [
          2043,
          0.0650914838706598
        ],
        [
          2044,
          0.0627595532413415
        ],
        [
          2045,
          0.0604276226120229
        ],
        [
          2046,
          0.0580956919827048
        ],
        [
          2047,
          0.055763761353386
        ],
        [
          2048,
          0.0534318307240677
        ],
        [
          2049,
          0.0510999000947492
        ],
        [
          2050,
          0.0487679694654308
        ]
      ]
    },
    {
      "seriesName": "INDBDL",
      "seriesValues": [
        [
          2023,
          0.019473845668097
        ],
        [
          2024,
          0.0219811230790192
        ],
        [
          2025,
          0.0243336167646291
        ],
        [
          2029,
          0.014855488536311232
        ],
        [
          2030,
          0.033774329312991
        ],
        [
          2031,
          0.0229298935684325
        ],
        [
          2032,
          0.024801839004545138
        ],
        [
          2033,
          0.0359924581641894
        ],
        [
          2034,
          0.0365667318075893
        ],
        [
          2035,
          0.0370584541308222
        ],
        [
          2036,
          0.0374676251338887
        ],
        [
          2037,
          0.0377942448167885
        ],
        [
          2038,
          0.0380383131795213
        ],
        [
          2039,
          0.038199830222088
        ],
        [
          2040,
          0.0382787959444877
        ],
        [
          2041,
          0.03827521034672
        ],
        [
          2042,
          0.0381890734287861
        ],
        [
          2043,
          0.0380203851906866
        ],
        [
          2044,
          0.0377691456324191
        ],
        [
          2045,
          0.0374353547539856
        ],
        [
          2046,
          0.0370190125553856
        ],
        [
          2047,
          0.0365201190366181
        ],
        [
          2048,
          0.0359386741976847
        ],
        [
          2049,
          0.0352746780385845
        ],
        [
          2050,
          0.034528130559317
        ]
      ]
    },
    {
      "seriesName": "INDBGS",
      "seriesValues": [
        [
          2023,
          0.0867131679336235
        ],
        [
          2024,
          0.1257876461356423
        ],
        [
          2025,
          0.1572280296294819
        ],
        [
          2026,
          0.08757688652015849
        ],
        [
          2028,
          2.2510990441058527e-06
        ],
        [
          2030,
          0.0066137531100583
        ],
        [
          2031,
          0.2279614743537886
        ],
        [
          2032,
          0.22273045237687558
        ],
        [
          2033,
          0.2462604052618693
        ],
        [
          2034,
          0.245029456619163
        ],
        [
          2035,
          0.2270951644291697
        ],
        [
          2036,
          0.2367241203609418
        ],
        [
          2037,
          0.2494310547281537
        ],
        [
          2038,
          0.2572547024244217
        ],
        [
          2039,
          0.2639483366520544
        ],
        [
          2040,
          0.4349507893832169
        ],
        [
          2041,
          0.4349100472819913
        ],
        [
          2042,
          0.433931298616421
        ],
        [
          2043,
          0.4320145433865074
        ],
        [
          2044,
          0.4291597815922485
        ],
        [
          2045,
          0.4253670132336468
        ],
        [
          2046,
          0.4206362383107
        ],
        [
          2047,
          0.4149674568234098
        ],
        [
          2048,
          0.4083606687717759
        ],
        [
          2049,
          0.4008158741557974
        ],
        [
          2050,
          0.3923155996110591
        ]
      ]
    },
    {
      "seriesName": "INDBKE",
      "seriesValues": [
        [
          2023,
          0.004462974302763509
        ],
        [
          2024,
          0.0050375867776466295
        ],
        [
          2025,
          0.005576726249388912
        ],
        [
          2030,
          0.007740328560982566
        ],
        [
          2031,
          0.007928696171440796
        ],
        [
          2032,
          0.008098144846890502
        ],
        [
          2033,
          0.008248674587332003
        ],
        [
          2034,
          0.008380285392764092
        ],
        [
          2035,
          0.008492977263188265
        ],
        [
          2036,
          0.008586750198603324
        ],
        [
          2037,
          0.008661604199010069
        ],
        [
          2038,
          0.008717539264408202
        ],
        [
          2039,
          0.008754555394797817
        ],
        [
          2040,
          0.00877265259017823
        ],
        [
          2041,
          0.008771830850550616
        ],
        [
          2042,
          0.008752090175913697
        ],
        [
          2043,
          0.008713430566268457
        ],
        [
          2044,
          0.00865585202161441
        ],
        [
          2045,
          0.008579354541952047
        ],
        [
          2046,
          0.008483938127280972
        ],
        [
          2047,
          0.008369602777601083
        ],
        [
          2048,
          0.00823634849291278
        ],
        [
          2049,
          0.008084175273215562
        ],
        [
          2050,
          0.007913083118509533
        ]
      ]
    }
  ]
}