{
  "name": "mitigation_sectoralcbs-led",
  "data": [
    {
      "seriesName": "RSD_BLD-XXX_NRGSRV-CD",
      "seriesValues": [
        [
          2018,
          1.7528219421826978
        ],
        [
          2019,
          1.8080585484911984
        ],
        [
          2020,
          1.8394989957935968
        ],
        [
          2021,
          1.870323785683195
        ],
        [
          2022,
          1.90014079640831
        ],
        [
          2023,
          1.752821942182692
        ],
        [
          2024,
          1.7528219421826903
        ],
        [
          2025,
          1.752821942182688
        ],
        [
          2026,
          1.7528219421826858
        ],
        [
          2027,
          1.752821942182683
        ],
        [
          2028,
          1.752821942182683
        ],
        [
          2029,
          1.752821942182683
        ],
        [
          2030,
          1.7528219421826825
        ],
        [
          2031,
          1.7528219421826827
        ],
        [
          2032,
          1.7528219421826827
        ],
        [
          2033,
          1.7528219421826827
        ],
        [
          2034,
          1.7528219421826825
        ],
        [
          2035,
          1.7528219421826823
        ],
        [
          2036,
          1.7528219421826825
        ],
        [
          2037,
          1.7528219421826825
        ],
        [
          2038,
          1.7528219421826825
        ],
        [
          2039,
          1.7528219421826825
        ],
        [
          2040,
          1.7528219421826823
        ],
        [
          2041,
          1.7528219421826825
        ],
        [
          2042,
          1.7528219421826825
        ],
        [
          2043,
          1.7528219421826825
        ],
        [
          2044,
          1.7528219421826825
        ],
        [
          2045,
          1.7528219421826825
        ],
        [
          2046,
          1.7528219421826823
        ],
        [
          2047,
          1.7528219421826825
        ],
        [
          2048,
          1.7528219421826825
        ],
        [
          2049,
          1.7528219421826825
        ],
        [
          2050,
          1.7528219421826825
        ]
      ]
    },
    {
      "seriesName": "RSD_BLD-XXX_NRGSRV-CK",
      "seriesValues": [
        [
          2018,
          2.7611554513679644
        ],
        [
          2019,
          2.9157456134021738
        ],
        [
          2020,
          3.0235061358434305
        ],
        [
          2021,
          3.1300550755773084
        ],
        [
          2022,
          3.2346207567924616
        ],
        [
          2023,
          3.0256691112732566
        ],
        [
          2024,
          3.1240185118065353
        ],
        [
          2025,
          3.181639681160896
        ],
        [
          2026,
          3.239330885592376
        ],
        [
          2027,
          3.296927256217336
        ],
        [
          2028,
          3.3549946895944203
        ],
        [
          2029,
          3.4130665078426543
        ],
        [
          2030,
          3.4263640945795917
        ],
        [
          2031,
          3.434064427162262
        ],
        [
          2032,
          3.441764759744933
        ],
        [
          2033,
          3.449465092327604
        ],
        [
          2034,
          3.449465092327604
        ],
        [
          2035,
          3.4494650923276042
        ],
        [
          2036,
          3.449465092327603
        ],
        [
          2037,
          3.449465092327603
        ],
        [
          2038,
          3.449465092327603
        ],
        [
          2039,
          3.449465092327603
        ],
        [
          2040,
          3.4494650923276042
        ],
        [
          2041,
          3.449465092327604
        ],
        [
          2042,
          3.4494650923276033
        ],
        [
          2043,
          3.353414205634443
        ],
        [
          2044,
          3.2561762525920988
        ],
        [
          2045,
          3.157980233420664
        ],
        [
          2046,
          3.0586043975289527
        ],
        [
          2047,
          2.9584154596894363
        ],
        [
          2048,
          2.857136367803231
        ],
        [
          2049,
          2.720952757658775
        ],
        [
          2050,
          2.5987672220195757
        ]
      ]
    },
    {
      "seriesName": "RSD_BLD-XXX_NRGSRV-CW",
      "seriesValues": [
        [
          2018,
          1.126811428382249
        ],
        [
          2019,
          1.1623205909249978
        ],
        [
          2020,
          1.1825322590249958
        ],
        [
          2021,
          1.2023481482999945
        ],
        [
          2022,
          1.2215161810799922
        ],
        [
          2023,
          1.12681142838224
        ],
        [
          2024,
          1.1268114283822377
        ],
        [
          2025,
          1.126811428382235
        ],
        [
          2026,
          1.1268114283822326
        ],
        [
          2027,
          1.1268114283822297
        ],
        [
          2028,
          1.12681142838223
        ],
        [
          2029,
          1.12681142838223
        ],
        [
          2030,
          1.12681142838223
        ],
        [
          2031,
          1.12681142838223
        ],
        [
          2032,
          1.12681142838223
        ],
        [
          2033,
          1.1268114283822297
        ],
        [
          2034,
          1.12681142838223
        ],
        [
          2035,
          1.1268114283822301
        ],
        [
          2036,
          1.1268114283822304
        ],
        [
          2037,
          1.12681142838223
        ],
        [
          2038,
          1.12681142838223
        ],
        [
          2039,
          1.12681142838223
        ],
        [
          2040,
          1.1268114283822297
        ],
        [
          2041,
          1.12681142838223
        ],
        [
          2042,
          1.12681142838223
        ],
        [
          2043,
          1.12681142838223
        ],
        [
          2044,
          1.1268114283822297
        ],
        [
          2045,
          1.1268114283822297
        ],
        [
          2046,
          1.1268114283822297
        ],
        [
          2047,
          1.1268114283822297
        ],
        [
          2048,
          1.1268114283822295
        ],
        [
          2049,
          1.1268114283822295
        ],
        [
          2050,
          1.1268114283822295
        ]
      ]
    },
    {
      "seriesName": "RSD_BLD-XXX_NRGSRV-DW",
      "seriesValues": [
        [
          2018,
          1.2125521732446025
        ],
        [
          2019,
          1.250763280379998
        ],
        [
          2020,
          1.2725128841399962
        ],
        [
          2021,
          1.2938365936799947
        ],
        [
          2022,
          1.3144631503679918
        ],
        [
          2023,
          1.2125521732445903
        ],
        [
          2024,
          1.212552173244588
        ],
        [
          2025,
          1.2125521732445859
        ],
        [
          2026,
          1.212552173244584
        ],
        [
          2027,
          1.2125521732445814
        ],
        [
          2028,
          1.2125521732445814
        ],
        [
          2029,
          1.2125521732445814
        ],
        [
          2030,
          1.2125521732445814
        ],
        [
          2031,
          1.2125521732445814
        ],
        [
          2032,
          1.2125521732445812
        ],
        [
          2033,
          1.2125521732445812
        ],
        [
          2034,
          1.2125521732445812
        ],
        [
          2035,
          1.2125521732445812
        ],
        [
          2036,
          1.2125521732445812
        ],
        [
          2037,
          1.2125521732445812
        ],
        [
          2038,
          1.2125521732445812
        ],
        [
          2039,
          1.212552173244581
        ],
        [
          2040,
          1.212552173244581
        ],
        [
          2041,
          1.212552173244581
        ],
        [
          2042,
          1.212552173244581
        ],
        [
          2043,
          1.212552173244581
        ],
        [
          2044,
          1.212552173244581
        ],
        [
          2045,
          1.212552173244581
        ],
        [
          2046,
          1.212552173244581
        ],
        [
          2047,
          1.212552173244581
        ],
        [
          2048,
          1.212552173244581
        ],
        [
          2049,
          1.2125521732445812
        ],
        [
          2050,
          1.2125521732445812
        ]
      ]
    },
    {
      "seriesName": "RSD_BLD-XXX_NRGSRV-LT",
      "seriesValues": [
        [
          2018,
          4.8797411246859905
        ],
        [
          2019,
          4.981872303312066
        ],
        [
          2020,
          5.013496863549001
        ],
        [
          2021,
          5.007962579951772
        ],
        [
          2022,
          4.990395146756166
        ],
        [
          2023,
          4.715337164077057
        ],
        [
          2024,
          4.541663227175993
        ],
        [
          2025,
          4.531886053005097
        ],
        [
          2026,
          4.536390524112328
        ],
        [
          2027,
          4.529890429447114
        ],
        [
          2028,
          4.497747940024293
        ],
        [
          2029,
          4.4202441575616644
        ],
        [
          2030,
          4.326378937149727
        ],
        [
          2031,
          4.257102323173945
        ],
        [
          2032,
          4.168140042708856
        ],
        [
          2033,
          3.840656110275164
        ],
        [
          2034,
          3.640733028248295
        ],
        [
          2035,
          3.620355970269693
        ],
        [
          2036,
          3.608188931499261
        ],
        [
          2037,
          3.588490896833161
        ],
        [
          2038,
          3.565438923857484
        ],
        [
          2039,
          3.5098221154700044
        ],
        [
          2040,
          3.44432505807017
        ],
        [
          2041,
          3.384151711237644
        ],
        [
          2042,
          3.3229322910097863
        ],
        [
          2043,
          3.1225295691777313
        ],
        [
          2044,
          2.993396122160836
        ],
        [
          2045,
          2.972554534122362
        ],
        [
          2046,
          2.9530828637063804
        ],
        [
          2047,
          2.928702863701221
        ],
        [
          2048,
          2.902198382049148
        ],
        [
          2049,
          2.8593845213865734
        ],
        [
          2050,
          2.8173353485987347
        ]
      ]
    },
    {
      "seriesName": "RSD_BLD-XXX_NRGSRV-OE",
      "seriesValues": [
        [
          2018,
          10.843443600154
        ],
        [
          2019,
          11.1851525956634
        ],
        [
          2020,
          11.379651939197775
        ],
        [
          2021,
          11.570342654900621
        ],
        [
          2022,
          11.75479896865513
        ],
        [
          2023,
          10.843443600153996
        ],
        [
          2024,
          10.843443600153998
        ],
        [
          2025,
          10.843443600153996
        ],
        [
          2026,
          10.843443600153996
        ],
        [
          2027,
          10.843443600153995
        ],
        [
          2028,
          10.843443600153995
        ],
        [
          2029,
          10.843443600153995
        ],
        [
          2030,
          10.843443600153996
        ],
        [
          2031,
          10.843443600153995
        ],
        [
          2032,
          10.843443600153995
        ],
        [
          2033,
          10.843443600153995
        ],
        [
          2034,
          10.843443600153996
        ],
        [
          2035,
          10.843443600153998
        ],
        [
          2036,
          10.843443600153998
        ],
        [
          2037,
          10.843443600153996
        ],
        [
          2038,
          10.843443600153995
        ],
        [
          2039,
          10.843443600153995
        ],
        [
          2040,
          10.843443600153995
        ],
        [
          2041,
          10.843443600153995
        ],
        [
          2042,
          10.843443600153995
        ],
        [
          2043,
          10.843443600153995
        ],
        [
          2044,
          10.843443600153996
        ],
        [
          2045,
          10.843443600153995
        ],
        [
          2046,
          10.843443600153995
        ],
        [
          2047,
          10.843443600153995
        ],
        [
          2048,
          10.843443600153995
        ],
        [
          2049,
          10.843443600153995
        ],
        [
          2050,
          10.843443600153995
        ]
      ]
    },
    {
      "seriesName": "RSD_BLD-XXX_NRGSRV-PF",
      "seriesValues": [
        [
          2018,
          1.1389592678360325
        ],
        [
          2019,
          1.1758986003926122
        ],
        [
          2020,
          1.1962268505317497
        ],
        [
          2021,
          1.2116967311512536
        ],
        [
          2022,
          1.2271226204414718
        ],
        [
          2023,
          1.5746178749356259
        ],
        [
          2024,
          1.7002301858413214
        ],
        [
          2025,
          1.8259607572725676
        ],
        [
          2026,
          1.9528166420073811
        ],
        [
          2027,
          2.080430798377515
        ],
        [
          2028,
          2.209820985040904
        ],
        [
          2029,
          2.3400946158624425
        ],
        [
          2030,
          2.47095303936975
        ],
        [
          2031,
          2.600456365951167
        ],
        [
          2032,
          2.731753766634093
        ],
        [
          2033,
          2.8639620796533696
        ],
        [
          2034,
          2.9968118606899585
        ],
        [
          2035,
          3.1297917167586724
        ],
        [
          2036,
          3.262873161204438
        ],
        [
          2037,
          3.39671142062169
        ],
        [
          2038,
          3.5311603015718576
        ],
        [
          2039,
          3.665431218214868
        ],
        [
          2040,
          3.7994001053751263
        ],
        [
          2041,
          3.9133241824039326
        ],
        [
          2042,
          4.047128276767082
        ],
        [
          2043,
          4.181559913162646
        ],
        [
          2044,
          4.316495336242702
        ],
        [
          2045,
          4.451556864240367
        ],
        [
          2046,
          4.586703082354697
        ],
        [
          2047,
          4.721846216910451
        ],
        [
          2048,
          4.856916824512919
        ],
        [
          2049,
          4.9917704942365235
        ],
        [
          2050,
          5.126365239501433
        ]
      ]
    },
    {
      "seriesName": "RSD_BLD-XXX_NRGSRV-RF",
      "seriesValues": [
        [
          2018,
          1.4430682741860004
        ],
        [
          2019,
          1.4885436257999982
        ],
        [
          2020,
          1.514428007399997
        ],
        [
          2021,
          1.5398055287999943
        ],
        [
          2022,
          1.5643533628799924
        ],
        [
          2023,
          1.4430682741859897
        ],
        [
          2024,
          1.443068274185988
        ],
        [
          2025,
          1.4430682741859864
        ],
        [
          2026,
          1.4430682741859842
        ],
        [
          2027,
          1.4430682741859822
        ],
        [
          2028,
          1.4430682741859822
        ],
        [
          2029,
          1.4430682741859822
        ],
        [
          2030,
          1.4430682741859822
        ],
        [
          2031,
          1.4430682741859822
        ],
        [
          2032,
          1.4430682741859822
        ],
        [
          2033,
          1.4430682741859822
        ],
        [
          2034,
          1.4411892427104116
        ],
        [
          2035,
          1.4390881166731453
        ],
        [
          2036,
          1.4365804661979937
        ],
        [
          2037,
          1.4336763319707455
        ],
        [
          2038,
          1.4332249253290867
        ],
        [
          2039,
          1.4300494694690198
        ],
        [
          2040,
          1.4265297907514933
        ],
        [
          2041,
          1.4224969146510948
        ],
        [
          2042,
          1.417954568993851
        ],
        [
          2043,
          1.412906441134817
        ],
        [
          2044,
          1.412906441134817
        ],
        [
          2045,
          1.412906441134817
        ],
        [
          2046,
          1.412906441134817
        ],
        [
          2047,
          1.412906441134817
        ],
        [
          2048,
          1.4129064411348167
        ],
        [
          2049,
          1.4042544662177867
        ],
        [
          2050,
          1.396344344665724
        ]
      ]
    },
    {
      "seriesName": "RSD_BLD-XXX_NRGSRV-WS",
      "seriesValues": [
        [
          2018,
          99.4508053115089
        ],
        [
          2019,
          98.73090516450846
        ],
        [
          2020,
          98.97827196262665
        ],
        [
          2021,
          98.43970782424674
        ],
        [
          2022,
          99.21716989042612
        ],
        [
          2023,
          95.23814256665516
        ],
        [
          2024,
          91.67618398218252
        ],
        [
          2025,
          90.38095613347309
        ],
        [
          2026,
          88.49568143675268
        ],
        [
          2027,
          86.64237439739945
        ],
        [
          2028,
          84.92717951554944
        ],
        [
          2029,
          82.51330966056065
        ],
        [
          2030,
          77.90111062127683
        ],
        [
          2031,
          75.59907415566873
        ],
        [
          2032,
          72.95117976190971
        ],
        [
          2033,
          71.30844508781708
        ],
        [
          2034,
          68.482509744382
        ],
        [
          2035,
          65.87712879757463
        ],
        [
          2036,
          62.9140342639394
        ],
        [
          2037,
          60.529273753652866
        ],
        [
          2038,
          58.250005872885325
        ],
        [
          2039,
          55.273904263097414
        ],
        [
          2040,
          52.58490248876818
        ],
        [
          2041,
          50.36325096970754
        ],
        [
          2042,
          48.283851230660204
        ],
        [
          2043,
          46.21255039963381
        ],
        [
          2044,
          44.3535459920068
        ],
        [
          2045,
          42.58624951287749
        ],
        [
          2046,
          40.86145165375773
        ],
        [
          2047,
          39.19632770826386
        ],
        [
          2048,
          37.54584268835054
        ],
        [
          2049,
          36.00912817896075
        ],
        [
          2050,
          34.18733064236075
        ]
      ]
    }
  ]
}