{
  "name": "mitigation_sectoralcbs-led_halfway",
  "data": [
    {
      "seriesName": "AGRCO2N",
      "seriesValues": [
        [
          2018,
          646.395099676456
        ],
        [
          2019,
          1292.954621813334
        ],
        [
          2020,
          1936.3101926870418
        ],
        [
          2021,
          2577.978858222185
        ],
        [
          2022,
          3217.7933507981147
        ],
        [
          2023,
          3961.7739570396197
        ],
        [
          2024,
          4709.8155689573205
        ],
        [
          2025,
          5458.290026534859
        ],
        [
          2026,
          6257.819284075153
        ],
        [
          2027,
          7052.73225446921
        ],
        [
          2028,
          7853.164786574574
        ],
        [
          2029,
          8645.44106721943
        ],
        [
          2030,
          9437.973945005835
        ],
        [
          2031,
          10094.309606403105
        ],
        [
          2032,
          10751.389198423192
        ],
        [
          2033,
          11410.598642027862
        ],
        [
          2034,
          12075.572859388532
        ],
        [
          2035,
          12740.595503792207
        ],
        [
          2036,
          13416.435365712921
        ],
        [
          2037,
          14101.96944648656
        ],
        [
          2038,
          14786.612027738181
        ],
        [
          2039,
          15470.45806724182
        ],
        [
          2040,
          16153.774951980005
        ],
        [
          2041,
          16835.895885444657
        ],
        [
          2042,
          17480.536062875537
        ],
        [
          2043,
          18093.691660122917
        ],
        [
          2044,
          18632.328762609537
        ],
        [
          2045,
          19074.46790571534
        ],
        [
          2046,
          19363.796539115247
        ],
        [
          2047,
          19579.61977791004
        ],
        [
          2048,
          19703.18357377004
        ],
        [
          2049,
          19807.313690857984
        ],
        [
          2050,
          19902.196052850086
        ]
      ]
    },
    {
      "seriesName": "INDCO2N",
      "seriesValues": [
        [
          2018,
          3938.55278615177
        ],
        [
          2019,
          7804.56283063436
        ],
        [
          2020,
          11549.87492677811
        ],
        [
          2021,
          15401.40397913613
        ],
        [
          2022,
          19544.44006175752
        ],
        [
          2023,
          23461.54021247181
        ],
        [
          2024,
          27232.933594621878
        ],
        [
          2025,
          29747.36084875599
        ],
        [
          2026,
          33390.51732903243
        ],
        [
          2027,
          36951.87045058897
        ],
        [
          2028,
          40501.579585492436
        ],
        [
          2029,
          43904.23398464561
        ],
        [
          2030,
          47139.22972310413
        ],
        [
          2031,
          49995.1491871084
        ],
        [
          2032,
          52770.67916365782
        ],
        [
          2033,
          55325.21215094203
        ],
        [
          2034,
          57619.59128985907
        ],
        [
          2035,
          59556.68095911856
        ],
        [
          2036,
          61114.08545781777
        ],
        [
          2037,
          62592.3256975603
        ],
        [
          2038,
          63990.23998506555
        ],
        [
          2039,
          65306.6666270529
        ],
        [
          2040,
          66540.44393024172
        ],
        [
          2041,
          67690.41020135142
        ],
        [
          2042,
          68755.40374710137
        ],
        [
          2043,
          69734.26287421098
        ],
        [
          2044,
          70625.82588939962
        ],
        [
          2045,
          71428.93109938668
        ],
        [
          2046,
          72142.41681089155
        ],
        [
          2047,
          72765.1213306336
        ],
        [
          2048,
          73295.88296533223
        ],
        [
          2049,
          73733.54002170684
        ],
        [
          2050,
          74077.03231551018
        ]
      ]
    },
    {
      "seriesName": "INDCO2P",
      "seriesValues": [
        [
          2018,
          2295.03666588256
        ],
        [
          2019,
          4246.64614645113
        ],
        [
          2020,
          6409.83596022017
        ],
        [
          2021,
          8835.95774288111
        ],
        [
          2022,
          11344.70171082892
        ],
        [
          2023,
          13733.2717341953
        ],
        [
          2024,
          16008.09873637885
        ],
        [
          2025,
          18190.47070439448
        ],
        [
          2026,
          20289.77138865869
        ],
        [
          2027,
          22313.13264857798
        ],
        [
          2028,
          24265.66941136444
        ],
        [
          2029,
          24412.14092841068
        ],
        [
          2030,
          24539.14741533791
        ],
        [
          2031,
          24670.899248523492
        ],
        [
          2032,
          24798.40465897801
        ],
        [
          2033,
          24925.22266397685
        ],
        [
          2034,
          25051.36370981002
        ],
        [
          2035,
          25176.76497521277
        ],
        [
          2036,
          25301.396206350186
        ],
        [
          2037,
          25425.22556390926
        ],
        [
          2038,
          25548.234789767805
        ],
        [
          2039,
          25670.372610295406
        ],
        [
          2040,
          25791.612662525382
        ],
        [
          2041,
          25930.732798406632
        ],
        [
          2042,
          26087.881771074462
        ],
        [
          2043,
          26263.20833366418
        ],
        [
          2044,
          26456.861239311085
        ],
        [
          2045,
          26668.989241150484
        ],
        [
          2046,
          26875.398574920997
        ],
        [
          2047,
          27076.03376501267
        ],
        [
          2048,
          27270.839335815563
        ],
        [
          2049,
          27459.75981171972
        ],
        [
          2050,
          27642.73971711519
        ]
      ]
    },
    {
      "seriesName": "PWRCO2N",
      "seriesValues": [
        [
          2018,
          11774.4208367599
        ],
        [
          2019,
          22123.7069798419
        ],
        [
          2020,
          31709.74473270506
        ],
        [
          2021,
          42310.41015049866
        ],
        [
          2022,
          54871.26355244076
        ],
        [
          2023,
          60650.91083320674
        ],
        [
          2024,
          66300.39864628973
        ],
        [
          2025,
          71709.86473270507
        ],
        [
          2026,
          77299.29211277897
        ],
        [
          2027,
          82633.83263523725
        ],
        [
          2028,
          86692.42085971049
        ],
        [
          2029,
          89328.30147937026
        ],
        [
          2030,
          90489.77472894253
        ],
        [
          2031,
          91089.06804839459
        ],
        [
          2032,
          91730.5761816607
        ],
        [
          2033,
          92435.24389461598
        ],
        [
          2034,
          93242.53167133949
        ],
        [
          2035,
          93473.90469927833
        ],
        [
          2036,
          93747.7512972409
        ],
        [
          2037,
          94084.43033498505
        ],
        [
          2038,
          94447.98033217294
        ],
        [
          2039,
          94851.60062289322
        ],
        [
          2040,
          95261.76682746211
        ],
        [
          2041,
          95667.76462068317
        ],
        [
          2042,
          96077.56825626343
        ],
        [
          2043,
          96469.01405288337
        ],
        [
          2044,
          96743.40352214039
        ],
        [
          2045,
          96954.86121104794
        ],
        [
          2046,
          97122.60948549394
        ],
        [
          2047,
          97226.94460192612
        ],
        [
          2048,
          97325.7743867074
        ],
        [
          2049,
          97403.28787300418
        ],
        [
          2050,
          97482.38214905217
        ]
      ]
    },
    {
      "seriesName": "RSDCO2",
      "seriesValues": [
        [
          2018,
          6767.26555333051
        ],
        [
          2019,
          13324.758809392879
        ],
        [
          2020,
          19801.78927148255
        ],
        [
          2021,
          26030.587034005708
        ],
        [
          2022,
          32407.45304730886
        ],
        [
          2023,
          39082.26696806262
        ],
        [
          2024,
          44905.3067639731
        ],
        [
          2025,
          48801.87627148256
        ],
        [
          2026,
          54011.98074439143
        ],
        [
          2027,
          58932.74989423657
        ],
        [
          2028,
          63563.32856537051
        ],
        [
          2029,
          67766.9042499444
        ],
        [
          2030,
          71801.94527148257
        ],
        [
          2031,
          75834.13998006046
        ],
        [
          2032,
          79719.13941148271
        ],
        [
          2033,
          83323.54174836577
        ],
        [
          2034,
          86465.53567172604
        ],
        [
          2035,
          89156.55982912391
        ],
        [
          2036,
          91234.84572098462
        ],
        [
          2037,
          92420.85430670525
        ],
        [
          2038,
          93388.5925775655
        ],
        [
          2039,
          94094.33708652518
        ],
        [
          2040,
          94583.43739748158
        ],
        [
          2041,
          95016.54449077093
        ],
        [
          2042,
          95284.80193591412
        ],
        [
          2043,
          95466.47782513715
        ],
        [
          2044,
          95568.340335764
        ],
        [
          2045,
          95651.77185439247
        ],
        [
          2046,
          95716.81319883348
        ],
        [
          2047,
          95763.56794047069
        ],
        [
          2048,
          95792.08403161306
        ],
        [
          2049,
          95796.39525900868
        ],
        [
          2050,
          95796.39525900868
        ]
      ]
    },
    {
      "seriesName": "SRVCO2N",
      "seriesValues": [
        [
          2018,
          1479.83736929787
        ],
        [
          2019,
          2933.52829006107
        ],
        [
          2020,
          4381.56055668896
        ],
        [
          2021,
          5963.6658948398
        ],
        [
          2022,
          7074.57318852042
        ],
        [
          2023,
          9019.684234808341
        ],
        [
          2024,
          10810.10898413904
        ],
        [
          2025,
          11381.581556688967
        ],
        [
          2026,
          12905.358252564616
        ],
        [
          2027,
          14118.784341552897
        ],
        [
          2028,
          14899.808081994137
        ],
        [
          2029,
          15615.19531918442
        ],
        [
          2030,
          16381.596556688972
        ],
        [
          2031,
          17254.449435234186
        ],
        [
          2032,
          18197.128118626948
        ],
        [
          2033,
          19224.42507510727
        ],
        [
          2034,
          20084.055677015283
        ],
        [
          2035,
          20391.65363128392
        ],
        [
          2036,
          20618.089002311684
        ],
        [
          2037,
          20832.695502285536
        ],
        [
          2038,
          21050.8534500058
        ],
        [
          2039,
          21263.51311345812
        ],
        [
          2040,
          21438.401415985878
        ],
        [
          2041,
          21574.06382704924
        ],
        [
          2042,
          21597.953495495156
        ],
        [
          2043,
          21597.953495495156
        ],
        [
          2044,
          21597.953495495156
        ],
        [
          2045,
          21597.953495495156
        ],
        [
          2046,
          21597.953495495156
        ],
        [
          2047,
          21597.953495495156
        ],
        [
          2048,
          21597.953495495156
        ],
        [
          2049,
          21597.953495495156
        ],
        [
          2050,
          21597.953495495156
        ]
      ]
    },
    {
      "seriesName": "TRACO2N",
      "seriesValues": [
        [
          2018,
          11665.956277527226
        ],
        [
          2019,
          23456.34423107334
        ],
        [
          2020,
          33148.35478938042
        ],
        [
          2021,
          43398.60971270523
        ],
        [
          2022,
          55555.70130408123
        ],
        [
          2023,
          66714.75409655896
        ],
        [
          2024,
          77112.27007317432
        ],
        [
          2025,
          87148.51678938036
        ],
        [
          2026,
          96171.42250487574
        ],
        [
          2027,
          104488.70142628108
        ],
        [
          2028,
          111906.43524368797
        ],
        [
          2029,
          118467.5644546735
        ],
        [
          2030,
          124148.62778938033
        ],
        [
          2031,
          129660.48284392424
        ],
        [
          2032,
          134511.3367928007
        ],
        [
          2033,
          138620.29689990633
        ],
        [
          2034,
          141903.0713756488
        ],
        [
          2035,
          144407.633145962
        ],
        [
          2036,
          146352.19062257058
        ],
        [
          2037,
          147936.22933438793
        ],
        [
          2038,
          149235.2475472535
        ],
        [
          2039,
          150332.31676292705
        ],
        [
          2040,
          151329.7726462487
        ],
        [
          2041,
          152251.9860690692
        ],
        [
          2042,
          153097.76261834076
        ],
        [
          2043,
          153878.16466701176
        ],
        [
          2044,
          154535.93026737552
        ],
        [
          2045,
          155141.09532689588
        ],
        [
          2046,
          155587.6025163394
        ],
        [
          2047,
          155906.56112239882
        ],
        [
          2048,
          156139.37655190774
        ],
        [
          2049,
          156313.4572243385
        ],
        [
          2050,
          156439.92344091085
        ]
      ]
    }
  ]
}